{ "_id" : { "$oid" : "54752b3873f0f20126964a79" }, "homedir" : "/home/user37142", "password" : 7749181, "username" : "user37142" }
{ "_id" : { "$oid" : "54752b3873f0f20126964a7a" }, "username" : "user58907", "password" : 5409590, "homedir" : "/home/user58907" }
{ "_id" : { "$oid" : "54752b3873f0f20126964a7b" }, "username" : "user11010", "password" : 4384747, "homedir" : "/home/user11010" }
{ "_id" : { "$oid" : "54752b3873f0f20126964a7c" }, "username" : "user58736", "password" : 5340819, "homedir" : "/home/user58736" }
{ "_id" : { "$oid" : "54752b3873f0f20126964a7d" }, "username" : "user77465", "password" : 9096262, "homedir" : "/home/user77465" }
{ "_id" : { "$oid" : "54752b3873f0f20126964a7e" }, "username" : "user19599", "password" : 6165307, "homedir" : "/home/user19599" }
{ "_id" : { "$oid" : "54752b3873f0f20126964a7f" }, "username" : "user73062", "password" : 5770516, "homedir" : "/home/user73062" }
{ "_id" : { "$oid" : "54752b3873f0f20126964a80" }, "username" : "user91988", "password" : 5287052, "homedir" : "/home/user91988" }
{ "_id" : { "$oid" : "54752b3873f0f20126964a81" }, "username" : "user30232", "password" : 3910578, "homedir" : "/home/user30232" }
{ "_id" : { "$oid" : "54752b3873f0f20126964a82" }, "username" : "user28501", "password" : 3155778, "homedir" : "/home/user28501" }
{ "_id" : { "$oid" : "54752b3873f0f20126964a83" }, "username" : "user87449", "password" : 8014780, "homedir" : "/home/user87449" }
{ "_id" : { "$oid" : "54752b3873f0f20126964a84" }, "username" : "user49489", "password" : 5275645, "homedir" : "/home/user49489" }
{ "_id" : { "$oid" : "54752b3873f0f20126964a85" }, "username" : "user35095", "password" : 5022372, "homedir" : "/home/user35095" }
{ "_id" : { "$oid" : "54752b3873f0f20126964a86" }, "username" : "user82654", "password" : 5961660, "homedir" : "/home/user82654" }
{ "_id" : { "$oid" : "54752b3873f0f20126964a87" }, "username" : "user97185", "password" : 4627118, "homedir" : "/home/user97185" }
{ "_id" : { "$oid" : "54752b3873f0f20126964a88" }, "username" : "user90667", "password" : 9346338, "homedir" : "/home/user90667" }
{ "_id" : { "$oid" : "54752b3873f0f20126964a89" }, "username" : "user89221", "password" : 8153395, "homedir" : "/home/user89221" }
{ "_id" : { "$oid" : "54752b3873f0f20126964a8a" }, "username" : "user10869", "password" : 5111528, "homedir" : "/home/user10869" }
{ "_id" : { "$oid" : "54752b3873f0f20126964a8b" }, "username" : "user86344", "password" : 5163998, "homedir" : "/home/user86344" }
{ "_id" : { "$oid" : "54752b3873f0f20126964a8c" }, "username" : "user15476", "password" : 9642924, "homedir" : "/home/user15476" }
{ "_id" : { "$oid" : "54752b3873f0f20126964a8d" }, "username" : "user92612", "password" : 7312721, "homedir" : "/home/user92612" }
{ "_id" : { "$oid" : "54752b3873f0f20126964a8e" }, "username" : "user99152", "password" : 9835317, "homedir" : "/home/user99152" }
{ "_id" : { "$oid" : "54752b3873f0f20126964a8f" }, "username" : "user12526", "password" : 2089204, "homedir" : "/home/user12526" }
{ "_id" : { "$oid" : "54752b3873f0f20126964a90" }, "username" : "user54317", "password" : 8150088, "homedir" : "/home/user54317" }
{ "_id" : { "$oid" : "54752b3873f0f20126964a91" }, "username" : "user83133", "password" : 9594666, "homedir" : "/home/user83133" }
{ "_id" : { "$oid" : "54752b3873f0f20126964a92" }, "username" : "user46169", "password" : 1087064, "homedir" : "/home/user46169" }
{ "_id" : { "$oid" : "54752b3873f0f20126964a93" }, "username" : "user55329", "password" : 6798413, "homedir" : "/home/user55329" }
{ "_id" : { "$oid" : "54752b3873f0f20126964a94" }, "username" : "user39845", "password" : 3356725, "homedir" : "/home/user39845" }
{ "_id" : { "$oid" : "54752b3873f0f20126964a95" }, "username" : "user59117", "password" : 8335671, "homedir" : "/home/user59117" }
{ "_id" : { "$oid" : "54752b3873f0f20126964a96" }, "username" : "user17025", "password" : 7047926, "homedir" : "/home/user17025" }
{ "_id" : { "$oid" : "54752b3873f0f20126964a97" }, "username" : "user42734", "password" : 1361435, "homedir" : "/home/user42734" }
{ "_id" : { "$oid" : "54752b3873f0f20126964a98" }, "username" : "user77153", "password" : 4328159, "homedir" : "/home/user77153" }
{ "_id" : { "$oid" : "54752b3873f0f20126964a99" }, "username" : "user63180", "password" : 3319803, "homedir" : "/home/user63180" }
{ "_id" : { "$oid" : "54752b3873f0f20126964a9a" }, "username" : "user18470", "password" : 8515597, "homedir" : "/home/user18470" }
{ "_id" : { "$oid" : "54752b3873f0f20126964a9b" }, "username" : "user19219", "password" : 7755056, "homedir" : "/home/user19219" }
{ "_id" : { "$oid" : "54752b3873f0f20126964a9c" }, "username" : "user97588", "password" : 8583091, "homedir" : "/home/user97588" }
{ "_id" : { "$oid" : "54752b3873f0f20126964a9d" }, "username" : "user30914", "password" : 1090729, "homedir" : "/home/user30914" }
{ "_id" : { "$oid" : "54752b3873f0f20126964a9e" }, "username" : "user28818", "password" : 6401951, "homedir" : "/home/user28818" }
{ "_id" : { "$oid" : "54752b3873f0f20126964a9f" }, "username" : "user55072", "password" : 6384221, "homedir" : "/home/user55072" }
{ "_id" : { "$oid" : "54752b3873f0f20126964aa0" }, "username" : "user53241", "password" : 2380998, "homedir" : "/home/user53241" }
{ "_id" : { "$oid" : "54752b3873f0f20126964aa1" }, "username" : "user98248", "password" : 5162746, "homedir" : "/home/user98248" }
{ "_id" : { "$oid" : "54752b3873f0f20126964aa2" }, "username" : "user94744", "password" : 8294995, "homedir" : "/home/user94744" }
{ "_id" : { "$oid" : "54752b3873f0f20126964aa3" }, "username" : "user57471", "password" : 8213456, "homedir" : "/home/user57471" }
{ "_id" : { "$oid" : "54752b3873f0f20126964aa4" }, "username" : "user92473", "password" : 1221181, "homedir" : "/home/user92473" }
{ "_id" : { "$oid" : "54752b3873f0f20126964aa5" }, "username" : "user21276", "password" : 6485223, "homedir" : "/home/user21276" }
{ "_id" : { "$oid" : "54752b3873f0f20126964aa6" }, "username" : "user12692", "password" : 3389859, "homedir" : "/home/user12692" }
{ "_id" : { "$oid" : "54752b3873f0f20126964aa7" }, "username" : "user50908", "password" : 7705682, "homedir" : "/home/user50908" }
{ "_id" : { "$oid" : "54752b3873f0f20126964aa8" }, "username" : "user22801", "password" : 2849316, "homedir" : "/home/user22801" }
{ "_id" : { "$oid" : "54752b3873f0f20126964aa9" }, "username" : "user40515", "password" : 4273041, "homedir" : "/home/user40515" }
{ "_id" : { "$oid" : "54752b3873f0f20126964aaa" }, "username" : "user68827", "password" : 6898349, "homedir" : "/home/user68827" }
{ "_id" : { "$oid" : "54752b3873f0f20126964aab" }, "username" : "user96395", "password" : 3924298, "homedir" : "/home/user96395" }
{ "_id" : { "$oid" : "54752b3873f0f20126964aac" }, "username" : "user82165", "password" : 1946864, "homedir" : "/home/user82165" }
{ "_id" : { "$oid" : "54752b3873f0f20126964aad" }, "username" : "user10426", "password" : 2623512, "homedir" : "/home/user10426" }
{ "_id" : { "$oid" : "54752b3873f0f20126964aae" }, "username" : "user70974", "password" : 4301315, "homedir" : "/home/user70974" }
{ "_id" : { "$oid" : "54752b3873f0f20126964aaf" }, "username" : "user87058", "password" : 9424638, "homedir" : "/home/user87058" }
{ "_id" : { "$oid" : "54752b3873f0f20126964ab0" }, "username" : "user12862", "password" : 6862094, "homedir" : "/home/user12862" }
{ "_id" : { "$oid" : "54752b3873f0f20126964ab1" }, "username" : "user63299", "password" : 2307324, "homedir" : "/home/user63299" }
{ "_id" : { "$oid" : "54752b3873f0f20126964ab2" }, "username" : "user62739", "password" : 8149542, "homedir" : "/home/user62739" }
{ "_id" : { "$oid" : "54752b3873f0f20126964ab3" }, "username" : "user59845", "password" : 8537048, "homedir" : "/home/user59845" }
{ "_id" : { "$oid" : "54752b3873f0f20126964ab4" }, "username" : "user88434", "password" : 5790240, "homedir" : "/home/user88434" }
{ "_id" : { "$oid" : "54752b3873f0f20126964ab5" }, "username" : "user80184", "password" : 7053329, "homedir" : "/home/user80184" }
{ "_id" : { "$oid" : "54752b3873f0f20126964ab6" }, "username" : "user50510", "password" : 9152409, "homedir" : "/home/user50510" }
{ "_id" : { "$oid" : "54752b3873f0f20126964ab7" }, "username" : "user28952", "password" : 9069198, "homedir" : "/home/user28952" }
{ "_id" : { "$oid" : "54752b3873f0f20126964ab8" }, "username" : "user39057", "password" : 2281237, "homedir" : "/home/user39057" }
{ "_id" : { "$oid" : "54752b3873f0f20126964ab9" }, "username" : "user47316", "password" : 4921732, "homedir" : "/home/user47316" }
{ "_id" : { "$oid" : "54752b3873f0f20126964aba" }, "username" : "user41471", "password" : 1223152, "homedir" : "/home/user41471" }
{ "_id" : { "$oid" : "54752b3873f0f20126964abb" }, "username" : "user31173", "password" : 1896064, "homedir" : "/home/user31173" }
{ "_id" : { "$oid" : "54752b3873f0f20126964abc" }, "username" : "user56066", "password" : 8622830, "homedir" : "/home/user56066" }
{ "_id" : { "$oid" : "54752b3873f0f20126964abd" }, "username" : "user39391", "password" : 8366096, "homedir" : "/home/user39391" }
{ "_id" : { "$oid" : "54752b3873f0f20126964abe" }, "username" : "user91658", "password" : 6732414, "homedir" : "/home/user91658" }
{ "_id" : { "$oid" : "54752b3873f0f20126964abf" }, "username" : "user46748", "password" : 5200005, "homedir" : "/home/user46748" }
{ "_id" : { "$oid" : "54752b3873f0f20126964ac0" }, "username" : "user10429", "password" : 1733866, "homedir" : "/home/user10429" }
{ "_id" : { "$oid" : "54752b3873f0f20126964ac1" }, "username" : "user33358", "password" : 3027466, "homedir" : "/home/user33358" }
{ "_id" : { "$oid" : "54752b3873f0f20126964ac2" }, "username" : "user44240", "password" : 2666070, "homedir" : "/home/user44240" }
{ "_id" : { "$oid" : "54752b3873f0f20126964ac3" }, "username" : "user32081", "password" : 9672385, "homedir" : "/home/user32081" }
{ "_id" : { "$oid" : "54752b3873f0f20126964ac4" }, "username" : "user24615", "password" : 9849378, "homedir" : "/home/user24615" }
{ "_id" : { "$oid" : "54752b3873f0f20126964ac5" }, "username" : "user93044", "password" : 9812478, "homedir" : "/home/user93044" }
{ "_id" : { "$oid" : "54752b3873f0f20126964ac6" }, "username" : "user86819", "password" : 6477385, "homedir" : "/home/user86819" }
{ "_id" : { "$oid" : "54752b3873f0f20126964ac7" }, "username" : "user34473", "password" : 4149814, "homedir" : "/home/user34473" }
{ "_id" : { "$oid" : "54752b3873f0f20126964ac8" }, "username" : "user57727", "password" : 8905183, "homedir" : "/home/user57727" }
{ "_id" : { "$oid" : "54752b3873f0f20126964ac9" }, "username" : "user98701", "password" : 1191504, "homedir" : "/home/user98701" }
{ "_id" : { "$oid" : "54752b3873f0f20126964aca" }, "username" : "user18742", "password" : 2594201, "homedir" : "/home/user18742" }
{ "_id" : { "$oid" : "54752b3873f0f20126964acb" }, "username" : "user28571", "password" : 8968845, "homedir" : "/home/user28571" }
{ "_id" : { "$oid" : "54752b3873f0f20126964acc" }, "username" : "user44193", "password" : 4597146, "homedir" : "/home/user44193" }
{ "_id" : { "$oid" : "54752b3873f0f20126964acd" }, "username" : "user92488", "password" : 1518886, "homedir" : "/home/user92488" }
{ "_id" : { "$oid" : "54752b3873f0f20126964ace" }, "username" : "user33835", "password" : 1722846, "homedir" : "/home/user33835" }
{ "_id" : { "$oid" : "54752b3873f0f20126964acf" }, "username" : "user74422", "password" : 5681786, "homedir" : "/home/user74422" }
{ "_id" : { "$oid" : "54752b3873f0f20126964ad0" }, "username" : "user19751", "password" : 6405799, "homedir" : "/home/user19751" }
{ "_id" : { "$oid" : "54752b3873f0f20126964ad1" }, "username" : "user29527", "password" : 4346968, "homedir" : "/home/user29527" }
{ "_id" : { "$oid" : "54752b3873f0f20126964ad2" }, "username" : "user93976", "password" : 3339784, "homedir" : "/home/user93976" }
{ "_id" : { "$oid" : "54752b3873f0f20126964ad3" }, "username" : "user65072", "password" : 1957016, "homedir" : "/home/user65072" }
{ "_id" : { "$oid" : "54752b3873f0f20126964ad4" }, "username" : "user51547", "password" : 6437392, "homedir" : "/home/user51547" }
{ "_id" : { "$oid" : "54752b3873f0f20126964ad5" }, "username" : "user69726", "password" : 7196724, "homedir" : "/home/user69726" }
{ "_id" : { "$oid" : "54752b3873f0f20126964ad6" }, "username" : "user11993", "password" : 8537483, "homedir" : "/home/user11993" }
{ "_id" : { "$oid" : "54752b3873f0f20126964ad7" }, "username" : "user33446", "password" : 8948584, "homedir" : "/home/user33446" }
{ "_id" : { "$oid" : "54752b3873f0f20126964ad8" }, "username" : "user42790", "password" : 6404162, "homedir" : "/home/user42790" }
{ "_id" : { "$oid" : "54752b3873f0f20126964ad9" }, "username" : "user77250", "password" : 3919476, "homedir" : "/home/user77250" }
{ "_id" : { "$oid" : "54752b3873f0f20126964ada" }, "username" : "user66366", "password" : 6069753, "homedir" : "/home/user66366" }
{ "_id" : { "$oid" : "54752b3873f0f20126964adb" }, "username" : "user60485", "password" : 2864481, "homedir" : "/home/user60485" }
{ "_id" : { "$oid" : "54752b3873f0f20126964adc" }, "username" : "user37716", "password" : 2050818, "homedir" : "/home/user37716" }
{ "_id" : { "$oid" : "54752b3873f0f20126964add" }, "username" : "user58940", "password" : 1345193, "homedir" : "/home/user58940" }
{ "_id" : { "$oid" : "54752b3873f0f20126964ade" }, "username" : "user28020", "password" : 8981736, "homedir" : "/home/user28020" }
{ "_id" : { "$oid" : "54752b3873f0f20126964adf" }, "username" : "user90319", "password" : 6091075, "homedir" : "/home/user90319" }
{ "_id" : { "$oid" : "54752b3873f0f20126964ae0" }, "username" : "user60960", "password" : 4566518, "homedir" : "/home/user60960" }
{ "_id" : { "$oid" : "54752b3873f0f20126964ae1" }, "username" : "user41200", "password" : 1543643, "homedir" : "/home/user41200" }
{ "_id" : { "$oid" : "54752b3873f0f20126964ae2" }, "username" : "user67853", "password" : 2952722, "homedir" : "/home/user67853" }
{ "_id" : { "$oid" : "54752b3873f0f20126964ae3" }, "username" : "user69364", "password" : 6058502, "homedir" : "/home/user69364" }
{ "_id" : { "$oid" : "54752b3873f0f20126964ae4" }, "username" : "user30827", "password" : 3774034, "homedir" : "/home/user30827" }
{ "_id" : { "$oid" : "54752b3873f0f20126964ae5" }, "username" : "user88437", "password" : 7409184, "homedir" : "/home/user88437" }
{ "_id" : { "$oid" : "54752b3873f0f20126964ae6" }, "username" : "user96570", "password" : 8016594, "homedir" : "/home/user96570" }
{ "_id" : { "$oid" : "54752b3873f0f20126964ae7" }, "username" : "user58192", "password" : 4369995, "homedir" : "/home/user58192" }
{ "_id" : { "$oid" : "54752b3873f0f20126964ae8" }, "username" : "user74052", "password" : 2234051, "homedir" : "/home/user74052" }
{ "_id" : { "$oid" : "54752b3973f0f20126964ae9" }, "username" : "user78797", "password" : 2048118, "homedir" : "/home/user78797" }
{ "_id" : { "$oid" : "54752b3973f0f20126964aea" }, "username" : "user21718", "password" : 8724531, "homedir" : "/home/user21718" }
{ "_id" : { "$oid" : "54752b3973f0f20126964aeb" }, "username" : "user37020", "password" : 2611400, "homedir" : "/home/user37020" }
{ "_id" : { "$oid" : "54752b3973f0f20126964aec" }, "username" : "user13796", "password" : 7134591, "homedir" : "/home/user13796" }
{ "_id" : { "$oid" : "54752b3973f0f20126964aed" }, "username" : "user10508", "password" : 4535404, "homedir" : "/home/user10508" }
{ "_id" : { "$oid" : "54752b3973f0f20126964aee" }, "username" : "user90903", "password" : 4606541, "homedir" : "/home/user90903" }
{ "_id" : { "$oid" : "54752b3973f0f20126964aef" }, "username" : "user67503", "password" : 9198292, "homedir" : "/home/user67503" }
{ "_id" : { "$oid" : "54752b3973f0f20126964af0" }, "username" : "user70513", "password" : 5306872, "homedir" : "/home/user70513" }
{ "_id" : { "$oid" : "54752b3973f0f20126964af1" }, "username" : "user40368", "password" : 6061401, "homedir" : "/home/user40368" }
{ "_id" : { "$oid" : "54752b3973f0f20126964af2" }, "username" : "user48508", "password" : 4109131, "homedir" : "/home/user48508" }
{ "_id" : { "$oid" : "54752b3973f0f20126964af3" }, "username" : "user70978", "password" : 8093358, "homedir" : "/home/user70978" }
{ "_id" : { "$oid" : "54752b3973f0f20126964af4" }, "username" : "user14852", "password" : 6650587, "homedir" : "/home/user14852" }
{ "_id" : { "$oid" : "54752b3973f0f20126964af5" }, "username" : "user74792", "password" : 1314810, "homedir" : "/home/user74792" }
{ "_id" : { "$oid" : "54752b3973f0f20126964af6" }, "username" : "user96530", "password" : 8540547, "homedir" : "/home/user96530" }
{ "_id" : { "$oid" : "54752b3973f0f20126964af7" }, "username" : "user26858", "password" : 4729750, "homedir" : "/home/user26858" }
{ "_id" : { "$oid" : "54752b3973f0f20126964af8" }, "username" : "user36494", "password" : 8966756, "homedir" : "/home/user36494" }
{ "_id" : { "$oid" : "54752b3973f0f20126964af9" }, "username" : "user10086", "password" : 8539758, "homedir" : "/home/user10086" }
{ "_id" : { "$oid" : "54752b3973f0f20126964afa" }, "username" : "user52944", "password" : 2882144, "homedir" : "/home/user52944" }
{ "_id" : { "$oid" : "54752b3973f0f20126964afb" }, "username" : "user26574", "password" : 7609252, "homedir" : "/home/user26574" }
{ "_id" : { "$oid" : "54752b3973f0f20126964afc" }, "username" : "user85836", "password" : 6593807, "homedir" : "/home/user85836" }
{ "_id" : { "$oid" : "54752b3973f0f20126964afd" }, "username" : "user11474", "password" : 4000176, "homedir" : "/home/user11474" }
{ "_id" : { "$oid" : "54752b3973f0f20126964afe" }, "username" : "user32139", "password" : 3589600, "homedir" : "/home/user32139" }
{ "_id" : { "$oid" : "54752b3973f0f20126964aff" }, "username" : "user55997", "password" : 1096161, "homedir" : "/home/user55997" }
{ "_id" : { "$oid" : "54752b3973f0f20126964b00" }, "username" : "user80826", "password" : 1729036, "homedir" : "/home/user80826" }
{ "_id" : { "$oid" : "54752b3973f0f20126964b01" }, "username" : "user82281", "password" : 5203643, "homedir" : "/home/user82281" }
{ "_id" : { "$oid" : "54752b3973f0f20126964b02" }, "username" : "user63396", "password" : 9517165, "homedir" : "/home/user63396" }
{ "_id" : { "$oid" : "54752b3973f0f20126964b03" }, "username" : "user98543", "password" : 4224100, "homedir" : "/home/user98543" }
{ "_id" : { "$oid" : "54752b3973f0f20126964b04" }, "username" : "user34913", "password" : 9480192, "homedir" : "/home/user34913" }
{ "_id" : { "$oid" : "54752b3973f0f20126964b05" }, "username" : "user98056", "password" : 5280715, "homedir" : "/home/user98056" }
{ "_id" : { "$oid" : "54752b3973f0f20126964b06" }, "username" : "user89247", "password" : 6026676, "homedir" : "/home/user89247" }
{ "_id" : { "$oid" : "54752b3973f0f20126964b07" }, "username" : "user38687", "password" : 1558353, "homedir" : "/home/user38687" }
{ "_id" : { "$oid" : "54752b3973f0f20126964b08" }, "username" : "user24053", "password" : 8803448, "homedir" : "/home/user24053" }
{ "_id" : { "$oid" : "54752b3973f0f20126964b09" }, "username" : "user76150", "password" : 2542703, "homedir" : "/home/user76150" }
{ "_id" : { "$oid" : "54752b3973f0f20126964b0a" }, "username" : "user30948", "password" : 1209150, "homedir" : "/home/user30948" }
{ "_id" : { "$oid" : "54752b3973f0f20126964b0b" }, "username" : "user90261", "password" : 1174133, "homedir" : "/home/user90261" }
{ "_id" : { "$oid" : "54752b3973f0f20126964b0c" }, "username" : "user30494", "password" : 9665722, "homedir" : "/home/user30494" }
{ "_id" : { "$oid" : "54752b3973f0f20126964b0d" }, "username" : "user99377", "password" : 5229776, "homedir" : "/home/user99377" }
{ "_id" : { "$oid" : "54752b3973f0f20126964b0e" }, "username" : "user64189", "password" : 8342362, "homedir" : "/home/user64189" }
{ "_id" : { "$oid" : "54752b3973f0f20126964b0f" }, "username" : "user95771", "password" : 6792456, "homedir" : "/home/user95771" }
{ "_id" : { "$oid" : "54752b3973f0f20126964b10" }, "username" : "user83538", "password" : 3878776, "homedir" : "/home/user83538" }
{ "_id" : { "$oid" : "54752b3973f0f20126964b11" }, "username" : "user76218", "password" : 7834982, "homedir" : "/home/user76218" }
{ "_id" : { "$oid" : "54752b3973f0f20126964b12" }, "username" : "user28721", "password" : 4042992, "homedir" : "/home/user28721" }
{ "_id" : { "$oid" : "54752b3973f0f20126964b13" }, "username" : "user57293", "password" : 4477259, "homedir" : "/home/user57293" }
{ "_id" : { "$oid" : "54752b3973f0f20126964b14" }, "username" : "user57861", "password" : 9718235, "homedir" : "/home/user57861" }
{ "_id" : { "$oid" : "54752b3973f0f20126964b15" }, "username" : "user71398", "password" : 7466459, "homedir" : "/home/user71398" }
{ "_id" : { "$oid" : "54752b3973f0f20126964b16" }, "username" : "user98457", "password" : 5861924, "homedir" : "/home/user98457" }
{ "_id" : { "$oid" : "54752b3973f0f20126964b17" }, "username" : "user86267", "password" : 6527395, "homedir" : "/home/user86267" }
{ "_id" : { "$oid" : "54752b3973f0f20126964b18" }, "username" : "user10032", "password" : 1306733, "homedir" : "/home/user10032" }
{ "_id" : { "$oid" : "54752b3973f0f20126964b19" }, "username" : "user39211", "password" : 7793103, "homedir" : "/home/user39211" }
{ "_id" : { "$oid" : "54752b3973f0f20126964b1a" }, "username" : "user47161", "password" : 7823490, "homedir" : "/home/user47161" }
{ "_id" : { "$oid" : "54752b3973f0f20126964b1b" }, "username" : "user88808", "password" : 1634905, "homedir" : "/home/user88808" }
{ "_id" : { "$oid" : "54752b3973f0f20126964b1c" }, "username" : "user16926", "password" : 1849533, "homedir" : "/home/user16926" }
{ "_id" : { "$oid" : "54752b3973f0f20126964b1d" }, "username" : "user81032", "password" : 9778391, "homedir" : "/home/user81032" }
{ "_id" : { "$oid" : "54752b3973f0f20126964b1e" }, "username" : "user97607", "password" : 5363182, "homedir" : "/home/user97607" }
{ "_id" : { "$oid" : "54752b3973f0f20126964b1f" }, "username" : "user78269", "password" : 5426141, "homedir" : "/home/user78269" }
{ "_id" : { "$oid" : "54752b3973f0f20126964b20" }, "username" : "user13759", "password" : 7666852, "homedir" : "/home/user13759" }
{ "_id" : { "$oid" : "54752b3973f0f20126964b21" }, "username" : "user91808", "password" : 3592943, "homedir" : "/home/user91808" }
{ "_id" : { "$oid" : "54752b3973f0f20126964b22" }, "username" : "user47363", "password" : 7476605, "homedir" : "/home/user47363" }
{ "_id" : { "$oid" : "54752b3973f0f20126964b23" }, "username" : "user54526", "password" : 6316901, "homedir" : "/home/user54526" }
{ "_id" : { "$oid" : "54752b3973f0f20126964b24" }, "username" : "user12051", "password" : 8435763, "homedir" : "/home/user12051" }
{ "_id" : { "$oid" : "54752b3973f0f20126964b25" }, "username" : "user99597", "password" : 9564405, "homedir" : "/home/user99597" }
{ "_id" : { "$oid" : "54752b3973f0f20126964b26" }, "username" : "user92689", "password" : 2398919, "homedir" : "/home/user92689" }
{ "_id" : { "$oid" : "54752b3973f0f20126964b27" }, "username" : "user91487", "password" : 9491787, "homedir" : "/home/user91487" }
{ "_id" : { "$oid" : "54752b3973f0f20126964b28" }, "username" : "user79686", "password" : 2560841, "homedir" : "/home/user79686" }
{ "_id" : { "$oid" : "54752b3973f0f20126964b29" }, "username" : "user41444", "password" : 7478148, "homedir" : "/home/user41444" }
{ "_id" : { "$oid" : "54752b3973f0f20126964b2a" }, "username" : "user27855", "password" : 5272434, "homedir" : "/home/user27855" }
{ "_id" : { "$oid" : "54752b3973f0f20126964b2b" }, "username" : "user74755", "password" : 4234088, "homedir" : "/home/user74755" }
{ "_id" : { "$oid" : "54752b3973f0f20126964b2c" }, "username" : "user35049", "password" : 4999409, "homedir" : "/home/user35049" }
{ "_id" : { "$oid" : "54752b3973f0f20126964b2d" }, "username" : "user31020", "password" : 3474306, "homedir" : "/home/user31020" }
{ "_id" : { "$oid" : "54752b3973f0f20126964b2e" }, "username" : "user94412", "password" : 5501088, "homedir" : "/home/user94412" }
{ "_id" : { "$oid" : "54752b3973f0f20126964b2f" }, "username" : "user28416", "password" : 9722061, "homedir" : "/home/user28416" }
{ "_id" : { "$oid" : "54752b3973f0f20126964b30" }, "username" : "user17598", "password" : 1449333, "homedir" : "/home/user17598" }
{ "_id" : { "$oid" : "54752b3973f0f20126964b31" }, "username" : "user83757", "password" : 2978103, "homedir" : "/home/user83757" }
{ "_id" : { "$oid" : "54752b3973f0f20126964b32" }, "username" : "user86479", "password" : 4870596, "homedir" : "/home/user86479" }
{ "_id" : { "$oid" : "54752b3973f0f20126964b33" }, "username" : "user67159", "password" : 6794154, "homedir" : "/home/user67159" }
{ "_id" : { "$oid" : "54752b3973f0f20126964b34" }, "username" : "user53167", "password" : 2581135, "homedir" : "/home/user53167" }
{ "_id" : { "$oid" : "54752b3973f0f20126964b35" }, "username" : "user79891", "password" : 6320954, "homedir" : "/home/user79891" }
{ "_id" : { "$oid" : "54752b3973f0f20126964b36" }, "username" : "user12684", "password" : 6188028, "homedir" : "/home/user12684" }
{ "_id" : { "$oid" : "54752b3973f0f20126964b37" }, "username" : "user69739", "password" : 5670491, "homedir" : "/home/user69739" }
{ "_id" : { "$oid" : "54752b3973f0f20126964b38" }, "username" : "user68804", "password" : 7891476, "homedir" : "/home/user68804" }
{ "_id" : { "$oid" : "54752b3973f0f20126964b39" }, "username" : "user31613", "password" : 8858559, "homedir" : "/home/user31613" }
{ "_id" : { "$oid" : "54752b3973f0f20126964b3a" }, "username" : "user28146", "password" : 7818013, "homedir" : "/home/user28146" }
{ "_id" : { "$oid" : "54752b3973f0f20126964b3b" }, "username" : "user20295", "password" : 5875407, "homedir" : "/home/user20295" }
{ "_id" : { "$oid" : "54752b3973f0f20126964b3c" }, "username" : "user47332", "password" : 3737329, "homedir" : "/home/user47332" }
{ "_id" : { "$oid" : "54752b3973f0f20126964b3d" }, "username" : "user74389", "password" : 3827094, "homedir" : "/home/user74389" }
{ "_id" : { "$oid" : "54752b3973f0f20126964b3e" }, "username" : "user90323", "password" : 9017870, "homedir" : "/home/user90323" }
{ "_id" : { "$oid" : "54752b3973f0f20126964b3f" }, "username" : "user23453", "password" : 1313246, "homedir" : "/home/user23453" }
{ "_id" : { "$oid" : "54752b3973f0f20126964b40" }, "username" : "user57342", "password" : 9590689, "homedir" : "/home/user57342" }
{ "_id" : { "$oid" : "54752b3973f0f20126964b41" }, "username" : "user91788", "password" : 6675661, "homedir" : "/home/user91788" }
{ "_id" : { "$oid" : "54752b3973f0f20126964b42" }, "username" : "user63286", "password" : 6620591, "homedir" : "/home/user63286" }
{ "_id" : { "$oid" : "54752b3973f0f20126964b43" }, "username" : "user60264", "password" : 8154231, "homedir" : "/home/user60264" }
{ "_id" : { "$oid" : "54752b3973f0f20126964b44" }, "username" : "user49348", "password" : 4976234, "homedir" : "/home/user49348" }
{ "_id" : { "$oid" : "54752b3973f0f20126964b45" }, "username" : "user45498", "password" : 7438192, "homedir" : "/home/user45498" }
{ "_id" : { "$oid" : "54752b3973f0f20126964b46" }, "username" : "user10713", "password" : 2989081, "homedir" : "/home/user10713" }
{ "_id" : { "$oid" : "54752b3973f0f20126964b47" }, "username" : "user29436", "password" : 8191951, "homedir" : "/home/user29436" }
{ "_id" : { "$oid" : "54752b3973f0f20126964b48" }, "username" : "user52260", "password" : 9757082, "homedir" : "/home/user52260" }
{ "_id" : { "$oid" : "54752b3973f0f20126964b49" }, "username" : "user81123", "password" : 5758944, "homedir" : "/home/user81123" }
{ "_id" : { "$oid" : "54752b3973f0f20126964b4a" }, "username" : "user74042", "password" : 3688768, "homedir" : "/home/user74042" }
{ "_id" : { "$oid" : "54752b3973f0f20126964b4b" }, "username" : "user71289", "password" : 5035122, "homedir" : "/home/user71289" }
{ "_id" : { "$oid" : "54752b3973f0f20126964b4c" }, "username" : "user99882", "password" : 5472811, "homedir" : "/home/user99882" }
{ "_id" : { "$oid" : "54752b3973f0f20126964b4d" }, "username" : "user43166", "password" : 4840000, "homedir" : "/home/user43166" }
{ "_id" : { "$oid" : "54752b3973f0f20126964b4e" }, "username" : "user39690", "password" : 8008653, "homedir" : "/home/user39690" }
{ "_id" : { "$oid" : "54752b3973f0f20126964b4f" }, "username" : "user56181", "password" : 2502495, "homedir" : "/home/user56181" }
{ "_id" : { "$oid" : "54752b3973f0f20126964b50" }, "username" : "user15289", "password" : 6485556, "homedir" : "/home/user15289" }
{ "_id" : { "$oid" : "54752b3973f0f20126964b51" }, "username" : "user69104", "password" : 2977273, "homedir" : "/home/user69104" }
{ "_id" : { "$oid" : "54752b3973f0f20126964b52" }, "username" : "user97949", "password" : 3199408, "homedir" : "/home/user97949" }
{ "_id" : { "$oid" : "54752b3973f0f20126964b53" }, "username" : "user99733", "password" : 4531270, "homedir" : "/home/user99733" }
{ "_id" : { "$oid" : "54752b3973f0f20126964b54" }, "username" : "user21059", "password" : 1382506, "homedir" : "/home/user21059" }
{ "_id" : { "$oid" : "54752b3973f0f20126964b55" }, "username" : "user45093", "password" : 9201454, "homedir" : "/home/user45093" }
{ "_id" : { "$oid" : "54752b3973f0f20126964b56" }, "username" : "user47765", "password" : 7373225, "homedir" : "/home/user47765" }
{ "_id" : { "$oid" : "54752b3973f0f20126964b57" }, "username" : "user37673", "password" : 3800305, "homedir" : "/home/user37673" }
{ "_id" : { "$oid" : "54752b3973f0f20126964b58" }, "username" : "user31566", "password" : 6885283, "homedir" : "/home/user31566" }
{ "_id" : { "$oid" : "54752b3973f0f20126964b59" }, "username" : "user16431", "password" : 7730132, "homedir" : "/home/user16431" }
{ "_id" : { "$oid" : "54752b3973f0f20126964b5a" }, "username" : "user75119", "password" : 9870343, "homedir" : "/home/user75119" }
{ "_id" : { "$oid" : "54752b3973f0f20126964b5b" }, "username" : "user54388", "password" : 9799674, "homedir" : "/home/user54388" }
{ "_id" : { "$oid" : "54752b3973f0f20126964b5c" }, "username" : "user65929", "password" : 4715998, "homedir" : "/home/user65929" }
{ "_id" : { "$oid" : "54752b3973f0f20126964b5d" }, "username" : "user77843", "password" : 7075075, "homedir" : "/home/user77843" }
{ "_id" : { "$oid" : "54752b3973f0f20126964b5e" }, "username" : "user76654", "password" : 1805281, "homedir" : "/home/user76654" }
{ "_id" : { "$oid" : "54752b3973f0f20126964b5f" }, "username" : "user95628", "password" : 5468524, "homedir" : "/home/user95628" }
{ "_id" : { "$oid" : "54752b3973f0f20126964b60" }, "username" : "user64512", "password" : 9224621, "homedir" : "/home/user64512" }
{ "_id" : { "$oid" : "54752b3973f0f20126964b61" }, "username" : "user34361", "password" : 3135538, "homedir" : "/home/user34361" }
{ "_id" : { "$oid" : "54752b3973f0f20126964b62" }, "username" : "user46902", "password" : 8037130, "homedir" : "/home/user46902" }
{ "_id" : { "$oid" : "54752b3973f0f20126964b63" }, "username" : "user95793", "password" : 3769483, "homedir" : "/home/user95793" }
{ "_id" : { "$oid" : "54752b3973f0f20126964b64" }, "username" : "user26717", "password" : 3691049, "homedir" : "/home/user26717" }
{ "_id" : { "$oid" : "54752b3973f0f20126964b65" }, "username" : "user61526", "password" : 4520437, "homedir" : "/home/user61526" }
{ "_id" : { "$oid" : "54752b3973f0f20126964b66" }, "username" : "user47022", "password" : 5831563, "homedir" : "/home/user47022" }
{ "_id" : { "$oid" : "54752b3973f0f20126964b67" }, "username" : "user26893", "password" : 7971694, "homedir" : "/home/user26893" }
{ "_id" : { "$oid" : "54752b3973f0f20126964b68" }, "username" : "user50492", "password" : 5500707, "homedir" : "/home/user50492" }
{ "_id" : { "$oid" : "54752b3973f0f20126964b69" }, "username" : "user98640", "password" : 5852639, "homedir" : "/home/user98640" }
{ "_id" : { "$oid" : "54752b3973f0f20126964b6a" }, "username" : "user94990", "password" : 8719436, "homedir" : "/home/user94990" }
{ "_id" : { "$oid" : "54752b3973f0f20126964b6b" }, "username" : "user24336", "password" : 3179332, "homedir" : "/home/user24336" }
{ "_id" : { "$oid" : "54752b3973f0f20126964b6c" }, "username" : "user13023", "password" : 7738467, "homedir" : "/home/user13023" }
{ "_id" : { "$oid" : "54752b3973f0f20126964b6d" }, "username" : "user97422", "password" : 4457938, "homedir" : "/home/user97422" }
{ "_id" : { "$oid" : "54752b3973f0f20126964b6e" }, "username" : "user16658", "password" : 1019576, "homedir" : "/home/user16658" }
{ "_id" : { "$oid" : "54752b3973f0f20126964b6f" }, "username" : "user17469", "password" : 7742087, "homedir" : "/home/user17469" }
{ "_id" : { "$oid" : "54752b3973f0f20126964b70" }, "username" : "user90322", "password" : 2884926, "homedir" : "/home/user90322" }
{ "_id" : { "$oid" : "54752b3973f0f20126964b71" }, "username" : "user43770", "password" : 3784380, "homedir" : "/home/user43770" }
{ "_id" : { "$oid" : "54752b3973f0f20126964b72" }, "username" : "user68307", "password" : 6078625, "homedir" : "/home/user68307" }
{ "_id" : { "$oid" : "54752b3973f0f20126964b73" }, "username" : "user94864", "password" : 4802510, "homedir" : "/home/user94864" }
{ "_id" : { "$oid" : "54752b3973f0f20126964b74" }, "username" : "user50960", "password" : 5322735, "homedir" : "/home/user50960" }
{ "_id" : { "$oid" : "54752b3973f0f20126964b75" }, "username" : "user15661", "password" : 8477854, "homedir" : "/home/user15661" }
{ "_id" : { "$oid" : "54752b3973f0f20126964b76" }, "username" : "user20616", "password" : 3296403, "homedir" : "/home/user20616" }
{ "_id" : { "$oid" : "54752b3973f0f20126964b77" }, "username" : "user49826", "password" : 7230660, "homedir" : "/home/user49826" }
{ "_id" : { "$oid" : "54752b3973f0f20126964b78" }, "username" : "user84106", "password" : 4726936, "homedir" : "/home/user84106" }
{ "_id" : { "$oid" : "54752b3973f0f20126964b79" }, "username" : "user45800", "password" : 9753103, "homedir" : "/home/user45800" }
{ "_id" : { "$oid" : "54752b3973f0f20126964b7a" }, "username" : "user94614", "password" : 9341123, "homedir" : "/home/user94614" }
{ "_id" : { "$oid" : "54752b3973f0f20126964b7b" }, "username" : "user18500", "password" : 5062837, "homedir" : "/home/user18500" }
{ "_id" : { "$oid" : "54752b3973f0f20126964b7c" }, "username" : "user91718", "password" : 2081646, "homedir" : "/home/user91718" }
{ "_id" : { "$oid" : "54752b3973f0f20126964b7d" }, "username" : "user78955", "password" : 1737536, "homedir" : "/home/user78955" }
{ "_id" : { "$oid" : "54752b3973f0f20126964b7e" }, "username" : "user24267", "password" : 7728612, "homedir" : "/home/user24267" }
{ "_id" : { "$oid" : "54752b3973f0f20126964b7f" }, "username" : "user85730", "password" : 1044866, "homedir" : "/home/user85730" }
{ "_id" : { "$oid" : "54752b3973f0f20126964b80" }, "username" : "user75638", "password" : 5558383, "homedir" : "/home/user75638" }
{ "_id" : { "$oid" : "54752b3973f0f20126964b81" }, "username" : "user52158", "password" : 6846917, "homedir" : "/home/user52158" }
{ "_id" : { "$oid" : "54752b3973f0f20126964b82" }, "username" : "user74183", "password" : 4869657, "homedir" : "/home/user74183" }
{ "_id" : { "$oid" : "54752b3973f0f20126964b83" }, "username" : "user33098", "password" : 9672318, "homedir" : "/home/user33098" }
{ "_id" : { "$oid" : "54752b3973f0f20126964b84" }, "username" : "user96086", "password" : 8458678, "homedir" : "/home/user96086" }
{ "_id" : { "$oid" : "54752b3973f0f20126964b85" }, "username" : "user85777", "password" : 9350893, "homedir" : "/home/user85777" }
{ "_id" : { "$oid" : "54752b3973f0f20126964b86" }, "username" : "user33047", "password" : 4659301, "homedir" : "/home/user33047" }
{ "_id" : { "$oid" : "54752b3973f0f20126964b87" }, "username" : "user26153", "password" : 6923621, "homedir" : "/home/user26153" }
{ "_id" : { "$oid" : "54752b3973f0f20126964b88" }, "username" : "user47682", "password" : 3899291, "homedir" : "/home/user47682" }
{ "_id" : { "$oid" : "54752b3973f0f20126964b89" }, "username" : "user58259", "password" : 2916675, "homedir" : "/home/user58259" }
{ "_id" : { "$oid" : "54752b3973f0f20126964b8a" }, "username" : "user59460", "password" : 8443960, "homedir" : "/home/user59460" }
{ "_id" : { "$oid" : "54752b3973f0f20126964b8b" }, "username" : "user42817", "password" : 6299627, "homedir" : "/home/user42817" }
{ "_id" : { "$oid" : "54752b3973f0f20126964b8c" }, "username" : "user44509", "password" : 6083929, "homedir" : "/home/user44509" }
{ "_id" : { "$oid" : "54752b3973f0f20126964b8d" }, "username" : "user89082", "password" : 3446015, "homedir" : "/home/user89082" }
{ "_id" : { "$oid" : "54752b3973f0f20126964b8e" }, "username" : "user20648", "password" : 9334269, "homedir" : "/home/user20648" }
{ "_id" : { "$oid" : "54752b3973f0f20126964b8f" }, "username" : "user27919", "password" : 7676670, "homedir" : "/home/user27919" }
{ "_id" : { "$oid" : "54752b3973f0f20126964b90" }, "username" : "user44481", "password" : 3342723, "homedir" : "/home/user44481" }
{ "_id" : { "$oid" : "54752b3973f0f20126964b91" }, "username" : "user57067", "password" : 6203915, "homedir" : "/home/user57067" }
{ "_id" : { "$oid" : "54752b3973f0f20126964b92" }, "username" : "user99672", "password" : 7643592, "homedir" : "/home/user99672" }
{ "_id" : { "$oid" : "54752b3973f0f20126964b93" }, "username" : "user13188", "password" : 3228758, "homedir" : "/home/user13188" }
{ "_id" : { "$oid" : "54752b3973f0f20126964b94" }, "username" : "user53165", "password" : 1474709, "homedir" : "/home/user53165" }
{ "_id" : { "$oid" : "54752b3973f0f20126964b95" }, "username" : "user16921", "password" : 6845109, "homedir" : "/home/user16921" }
{ "_id" : { "$oid" : "54752b3973f0f20126964b96" }, "username" : "user43174", "password" : 9657633, "homedir" : "/home/user43174" }
{ "_id" : { "$oid" : "54752b3973f0f20126964b97" }, "username" : "user76755", "password" : 6796592, "homedir" : "/home/user76755" }
{ "_id" : { "$oid" : "54752b3973f0f20126964b98" }, "username" : "user44944", "password" : 8921299, "homedir" : "/home/user44944" }
{ "_id" : { "$oid" : "54752b3973f0f20126964b99" }, "username" : "user95384", "password" : 4671080, "homedir" : "/home/user95384" }
{ "_id" : { "$oid" : "54752b3973f0f20126964b9a" }, "username" : "user90580", "password" : 7881675, "homedir" : "/home/user90580" }
{ "_id" : { "$oid" : "54752b3973f0f20126964b9b" }, "username" : "user89978", "password" : 5644374, "homedir" : "/home/user89978" }
{ "_id" : { "$oid" : "54752b3973f0f20126964b9c" }, "username" : "user99020", "password" : 9298837, "homedir" : "/home/user99020" }
{ "_id" : { "$oid" : "54752b3973f0f20126964b9d" }, "username" : "user18835", "password" : 4867293, "homedir" : "/home/user18835" }
{ "_id" : { "$oid" : "54752b3973f0f20126964b9e" }, "username" : "user73166", "password" : 4915960, "homedir" : "/home/user73166" }
{ "_id" : { "$oid" : "54752b3973f0f20126964b9f" }, "username" : "user71467", "password" : 2248051, "homedir" : "/home/user71467" }
{ "_id" : { "$oid" : "54752b3973f0f20126964ba0" }, "username" : "user99798", "password" : 4441246, "homedir" : "/home/user99798" }
{ "_id" : { "$oid" : "54752b3973f0f20126964ba1" }, "username" : "user36539", "password" : 4174888, "homedir" : "/home/user36539" }
{ "_id" : { "$oid" : "54752b3973f0f20126964ba2" }, "username" : "user29195", "password" : 6552378, "homedir" : "/home/user29195" }
{ "_id" : { "$oid" : "54752b3973f0f20126964ba3" }, "username" : "user90815", "password" : 7072917, "homedir" : "/home/user90815" }
{ "_id" : { "$oid" : "54752b3973f0f20126964ba4" }, "username" : "user49040", "password" : 8980914, "homedir" : "/home/user49040" }
{ "_id" : { "$oid" : "54752b3973f0f20126964ba5" }, "username" : "user79462", "password" : 4107644, "homedir" : "/home/user79462" }
{ "_id" : { "$oid" : "54752b3973f0f20126964ba6" }, "username" : "user45192", "password" : 2266299, "homedir" : "/home/user45192" }
{ "_id" : { "$oid" : "54752b3973f0f20126964ba7" }, "username" : "user38088", "password" : 6688765, "homedir" : "/home/user38088" }
{ "_id" : { "$oid" : "54752b3973f0f20126964ba8" }, "username" : "user33153", "password" : 2584253, "homedir" : "/home/user33153" }
{ "_id" : { "$oid" : "54752b3973f0f20126964ba9" }, "username" : "user92467", "password" : 9371848, "homedir" : "/home/user92467" }
{ "_id" : { "$oid" : "54752b3973f0f20126964baa" }, "username" : "user94975", "password" : 4430297, "homedir" : "/home/user94975" }
{ "_id" : { "$oid" : "54752b3973f0f20126964bab" }, "username" : "user51844", "password" : 6722730, "homedir" : "/home/user51844" }
{ "_id" : { "$oid" : "54752b3973f0f20126964bac" }, "username" : "user45428", "password" : 2344186, "homedir" : "/home/user45428" }
{ "_id" : { "$oid" : "54752b3973f0f20126964bad" }, "username" : "user73567", "password" : 6412111, "homedir" : "/home/user73567" }
{ "_id" : { "$oid" : "54752b3973f0f20126964bae" }, "username" : "user77964", "password" : 8087840, "homedir" : "/home/user77964" }
{ "_id" : { "$oid" : "54752b3973f0f20126964baf" }, "username" : "user98828", "password" : 1287670, "homedir" : "/home/user98828" }
{ "_id" : { "$oid" : "54752b3973f0f20126964bb0" }, "username" : "user14621", "password" : 5442613, "homedir" : "/home/user14621" }
{ "_id" : { "$oid" : "54752b3973f0f20126964bb1" }, "username" : "user13408", "password" : 4136223, "homedir" : "/home/user13408" }
{ "_id" : { "$oid" : "54752b3973f0f20126964bb2" }, "username" : "user55575", "password" : 3788187, "homedir" : "/home/user55575" }
{ "_id" : { "$oid" : "54752b3973f0f20126964bb3" }, "username" : "user40062", "password" : 3995411, "homedir" : "/home/user40062" }
{ "_id" : { "$oid" : "54752b3973f0f20126964bb4" }, "username" : "user31503", "password" : 7068925, "homedir" : "/home/user31503" }
{ "_id" : { "$oid" : "54752b3973f0f20126964bb5" }, "username" : "user95064", "password" : 5820851, "homedir" : "/home/user95064" }
{ "_id" : { "$oid" : "54752b3973f0f20126964bb6" }, "username" : "user61133", "password" : 4782899, "homedir" : "/home/user61133" }
{ "_id" : { "$oid" : "54752b3973f0f20126964bb7" }, "username" : "user73288", "password" : 8031943, "homedir" : "/home/user73288" }
{ "_id" : { "$oid" : "54752b3973f0f20126964bb8" }, "username" : "user44085", "password" : 1936089, "homedir" : "/home/user44085" }
{ "_id" : { "$oid" : "54752b3973f0f20126964bb9" }, "username" : "user69272", "password" : 2155528, "homedir" : "/home/user69272" }
{ "_id" : { "$oid" : "54752b3973f0f20126964bba" }, "username" : "user18204", "password" : 9014507, "homedir" : "/home/user18204" }
{ "_id" : { "$oid" : "54752b3973f0f20126964bbb" }, "username" : "user64013", "password" : 2631641, "homedir" : "/home/user64013" }
{ "_id" : { "$oid" : "54752b3973f0f20126964bbc" }, "username" : "user41483", "password" : 7005801, "homedir" : "/home/user41483" }
{ "_id" : { "$oid" : "54752b3973f0f20126964bbd" }, "username" : "user28704", "password" : 5976026, "homedir" : "/home/user28704" }
{ "_id" : { "$oid" : "54752b3973f0f20126964bbe" }, "username" : "user96091", "password" : 9041176, "homedir" : "/home/user96091" }
{ "_id" : { "$oid" : "54752b3973f0f20126964bbf" }, "username" : "user41686", "password" : 8498436, "homedir" : "/home/user41686" }
{ "_id" : { "$oid" : "54752b3973f0f20126964bc0" }, "username" : "user42591", "password" : 3630888, "homedir" : "/home/user42591" }
{ "_id" : { "$oid" : "54752b3973f0f20126964bc1" }, "username" : "user95609", "password" : 8593085, "homedir" : "/home/user95609" }
{ "_id" : { "$oid" : "54752b3973f0f20126964bc2" }, "username" : "user36625", "password" : 9627438, "homedir" : "/home/user36625" }
{ "_id" : { "$oid" : "54752b3973f0f20126964bc3" }, "username" : "user11224", "password" : 3009290, "homedir" : "/home/user11224" }
{ "_id" : { "$oid" : "54752b3973f0f20126964bc4" }, "username" : "user46727", "password" : 9947700, "homedir" : "/home/user46727" }
{ "_id" : { "$oid" : "54752b3973f0f20126964bc5" }, "username" : "user13419", "password" : 6712737, "homedir" : "/home/user13419" }
{ "_id" : { "$oid" : "54752b3973f0f20126964bc6" }, "username" : "user67923", "password" : 2721131, "homedir" : "/home/user67923" }
{ "_id" : { "$oid" : "54752b3973f0f20126964bc7" }, "username" : "user14799", "password" : 5414998, "homedir" : "/home/user14799" }
{ "_id" : { "$oid" : "54752b3973f0f20126964bc8" }, "username" : "user21249", "password" : 1273383, "homedir" : "/home/user21249" }
{ "_id" : { "$oid" : "54752b3973f0f20126964bc9" }, "username" : "user92337", "password" : 6353501, "homedir" : "/home/user92337" }
{ "_id" : { "$oid" : "54752b3973f0f20126964bca" }, "username" : "user28241", "password" : 4725450, "homedir" : "/home/user28241" }
{ "_id" : { "$oid" : "54752b3973f0f20126964bcb" }, "username" : "user72676", "password" : 8507374, "homedir" : "/home/user72676" }
{ "_id" : { "$oid" : "54752b3973f0f20126964bcc" }, "username" : "user91619", "password" : 8813551, "homedir" : "/home/user91619" }
{ "_id" : { "$oid" : "54752b3973f0f20126964bcd" }, "username" : "user91150", "password" : 7164030, "homedir" : "/home/user91150" }
{ "_id" : { "$oid" : "54752b3973f0f20126964bce" }, "username" : "user90056", "password" : 5341889, "homedir" : "/home/user90056" }
{ "_id" : { "$oid" : "54752b3973f0f20126964bcf" }, "username" : "user37214", "password" : 3145792, "homedir" : "/home/user37214" }
{ "_id" : { "$oid" : "54752b3973f0f20126964bd0" }, "username" : "user20012", "password" : 8563739, "homedir" : "/home/user20012" }
{ "_id" : { "$oid" : "54752b3973f0f20126964bd1" }, "username" : "user89296", "password" : 1745355, "homedir" : "/home/user89296" }
{ "_id" : { "$oid" : "54752b3973f0f20126964bd2" }, "username" : "user94833", "password" : 7120800, "homedir" : "/home/user94833" }
{ "_id" : { "$oid" : "54752b3973f0f20126964bd3" }, "username" : "user21062", "password" : 7949970, "homedir" : "/home/user21062" }
{ "_id" : { "$oid" : "54752b3973f0f20126964bd4" }, "username" : "user73851", "password" : 4496039, "homedir" : "/home/user73851" }
{ "_id" : { "$oid" : "54752b3973f0f20126964bd5" }, "username" : "user22039", "password" : 2187118, "homedir" : "/home/user22039" }
{ "_id" : { "$oid" : "54752b3973f0f20126964bd6" }, "username" : "user89169", "password" : 1441255, "homedir" : "/home/user89169" }
{ "_id" : { "$oid" : "54752b3973f0f20126964bd7" }, "username" : "user58015", "password" : 7328630, "homedir" : "/home/user58015" }
{ "_id" : { "$oid" : "54752b3973f0f20126964bd8" }, "username" : "user48965", "password" : 2202133, "homedir" : "/home/user48965" }
{ "_id" : { "$oid" : "54752b3973f0f20126964bd9" }, "username" : "user67074", "password" : 9737964, "homedir" : "/home/user67074" }
{ "_id" : { "$oid" : "54752b3973f0f20126964bda" }, "username" : "user12425", "password" : 8526053, "homedir" : "/home/user12425" }
{ "_id" : { "$oid" : "54752b3973f0f20126964bdb" }, "username" : "user47008", "password" : 1217469, "homedir" : "/home/user47008" }
{ "_id" : { "$oid" : "54752b3973f0f20126964bdc" }, "username" : "user91321", "password" : 8924204, "homedir" : "/home/user91321" }
{ "_id" : { "$oid" : "54752b3973f0f20126964bdd" }, "username" : "user89645", "password" : 4676933, "homedir" : "/home/user89645" }
{ "_id" : { "$oid" : "54752b3973f0f20126964bde" }, "username" : "user86654", "password" : 7479844, "homedir" : "/home/user86654" }
{ "_id" : { "$oid" : "54752b3973f0f20126964bdf" }, "username" : "user71478", "password" : 4499634, "homedir" : "/home/user71478" }
{ "_id" : { "$oid" : "54752b3973f0f20126964be0" }, "username" : "user73086", "password" : 5195264, "homedir" : "/home/user73086" }
{ "_id" : { "$oid" : "54752b3973f0f20126964be1" }, "username" : "user57234", "password" : 3981426, "homedir" : "/home/user57234" }
{ "_id" : { "$oid" : "54752b3973f0f20126964be2" }, "username" : "user35005", "password" : 8939854, "homedir" : "/home/user35005" }
{ "_id" : { "$oid" : "54752b3973f0f20126964be3" }, "username" : "user60853", "password" : 2880492, "homedir" : "/home/user60853" }
{ "_id" : { "$oid" : "54752b3973f0f20126964be4" }, "username" : "user57098", "password" : 7334425, "homedir" : "/home/user57098" }
{ "_id" : { "$oid" : "54752b3973f0f20126964be5" }, "username" : "user44914", "password" : 2599757, "homedir" : "/home/user44914" }
{ "_id" : { "$oid" : "54752b3973f0f20126964be6" }, "username" : "user60527", "password" : 2774147, "homedir" : "/home/user60527" }
{ "_id" : { "$oid" : "54752b3973f0f20126964be7" }, "username" : "user95400", "password" : 7940878, "homedir" : "/home/user95400" }
{ "_id" : { "$oid" : "54752b3973f0f20126964be8" }, "username" : "user74073", "password" : 3282593, "homedir" : "/home/user74073" }
{ "_id" : { "$oid" : "54752b3973f0f20126964be9" }, "username" : "user58422", "password" : 7064229, "homedir" : "/home/user58422" }
{ "_id" : { "$oid" : "54752b3973f0f20126964bea" }, "username" : "user66510", "password" : 4718396, "homedir" : "/home/user66510" }
{ "_id" : { "$oid" : "54752b3973f0f20126964beb" }, "username" : "user36936", "password" : 9631470, "homedir" : "/home/user36936" }
{ "_id" : { "$oid" : "54752b3973f0f20126964bec" }, "username" : "user20253", "password" : 4740431, "homedir" : "/home/user20253" }
{ "_id" : { "$oid" : "54752b3973f0f20126964bed" }, "username" : "user20447", "password" : 8598745, "homedir" : "/home/user20447" }
{ "_id" : { "$oid" : "54752b3973f0f20126964bee" }, "username" : "user83396", "password" : 5177232, "homedir" : "/home/user83396" }
{ "_id" : { "$oid" : "54752b3973f0f20126964bef" }, "username" : "user44076", "password" : 3713687, "homedir" : "/home/user44076" }
{ "_id" : { "$oid" : "54752b3973f0f20126964bf0" }, "username" : "user31345", "password" : 9642851, "homedir" : "/home/user31345" }
{ "_id" : { "$oid" : "54752b3973f0f20126964bf1" }, "username" : "user43533", "password" : 3583969, "homedir" : "/home/user43533" }
{ "_id" : { "$oid" : "54752b3973f0f20126964bf2" }, "username" : "user37727", "password" : 4126597, "homedir" : "/home/user37727" }
{ "_id" : { "$oid" : "54752b3973f0f20126964bf3" }, "username" : "user89994", "password" : 5688382, "homedir" : "/home/user89994" }
{ "_id" : { "$oid" : "54752b3973f0f20126964bf4" }, "username" : "user74652", "password" : 6658267, "homedir" : "/home/user74652" }
{ "_id" : { "$oid" : "54752b3973f0f20126964bf5" }, "username" : "user39181", "password" : 7156558, "homedir" : "/home/user39181" }
{ "_id" : { "$oid" : "54752b3973f0f20126964bf6" }, "username" : "user79072", "password" : 9302627, "homedir" : "/home/user79072" }
{ "_id" : { "$oid" : "54752b3973f0f20126964bf7" }, "username" : "user45660", "password" : 2235499, "homedir" : "/home/user45660" }
{ "_id" : { "$oid" : "54752b3973f0f20126964bf8" }, "username" : "user73779", "password" : 4106278, "homedir" : "/home/user73779" }
{ "_id" : { "$oid" : "54752b3973f0f20126964bf9" }, "username" : "user84832", "password" : 6111544, "homedir" : "/home/user84832" }
{ "_id" : { "$oid" : "54752b3973f0f20126964bfa" }, "username" : "user73783", "password" : 1607631, "homedir" : "/home/user73783" }
{ "_id" : { "$oid" : "54752b3973f0f20126964bfb" }, "username" : "user81475", "password" : 8301866, "homedir" : "/home/user81475" }
{ "_id" : { "$oid" : "54752b3973f0f20126964bfc" }, "username" : "user33072", "password" : 4447870, "homedir" : "/home/user33072" }
{ "_id" : { "$oid" : "54752b3973f0f20126964bfd" }, "username" : "user85911", "password" : 6504645, "homedir" : "/home/user85911" }
{ "_id" : { "$oid" : "54752b3a73f0f20126964bfe" }, "username" : "user14276", "password" : 4511160, "homedir" : "/home/user14276" }
{ "_id" : { "$oid" : "54752b3a73f0f20126964bff" }, "username" : "user43006", "password" : 9105899, "homedir" : "/home/user43006" }
{ "_id" : { "$oid" : "54752b3a73f0f20126964c00" }, "username" : "user30317", "password" : 3187809, "homedir" : "/home/user30317" }
{ "_id" : { "$oid" : "54752b3a73f0f20126964c01" }, "username" : "user62371", "password" : 3340813, "homedir" : "/home/user62371" }
{ "_id" : { "$oid" : "54752b3a73f0f20126964c02" }, "username" : "user13050", "password" : 5100037, "homedir" : "/home/user13050" }
{ "_id" : { "$oid" : "54752b3a73f0f20126964c03" }, "username" : "user89968", "password" : 9285126, "homedir" : "/home/user89968" }
{ "_id" : { "$oid" : "54752b3a73f0f20126964c04" }, "username" : "user50982", "password" : 8553276, "homedir" : "/home/user50982" }
{ "_id" : { "$oid" : "54752b3a73f0f20126964c05" }, "username" : "user83324", "password" : 5421390, "homedir" : "/home/user83324" }
{ "_id" : { "$oid" : "54752b3a73f0f20126964c06" }, "username" : "user17890", "password" : 8734570, "homedir" : "/home/user17890" }
{ "_id" : { "$oid" : "54752b3a73f0f20126964c07" }, "username" : "user81881", "password" : 6260946, "homedir" : "/home/user81881" }
{ "_id" : { "$oid" : "54752b3a73f0f20126964c08" }, "username" : "user87286", "password" : 4285290, "homedir" : "/home/user87286" }
{ "_id" : { "$oid" : "54752b3a73f0f20126964c09" }, "username" : "user58328", "password" : 9018906, "homedir" : "/home/user58328" }
{ "_id" : { "$oid" : "54752b3a73f0f20126964c0a" }, "username" : "user16757", "password" : 7778733, "homedir" : "/home/user16757" }
{ "_id" : { "$oid" : "54752b3a73f0f20126964c0b" }, "username" : "user58007", "password" : 8156630, "homedir" : "/home/user58007" }
{ "_id" : { "$oid" : "54752b3a73f0f20126964c0c" }, "username" : "user93910", "password" : 6064351, "homedir" : "/home/user93910" }
{ "_id" : { "$oid" : "54752b3a73f0f20126964c0d" }, "username" : "user79667", "password" : 4054807, "homedir" : "/home/user79667" }
{ "_id" : { "$oid" : "54752b3a73f0f20126964c0e" }, "username" : "user18678", "password" : 6973337, "homedir" : "/home/user18678" }
{ "_id" : { "$oid" : "54752b3a73f0f20126964c0f" }, "username" : "user33572", "password" : 7412036, "homedir" : "/home/user33572" }
{ "_id" : { "$oid" : "54752b3a73f0f20126964c10" }, "username" : "user90325", "password" : 4805685, "homedir" : "/home/user90325" }
{ "_id" : { "$oid" : "54752b3a73f0f20126964c11" }, "username" : "user68550", "password" : 5175667, "homedir" : "/home/user68550" }
{ "_id" : { "$oid" : "54752b3a73f0f20126964c12" }, "username" : "user10531", "password" : 6107282, "homedir" : "/home/user10531" }
{ "_id" : { "$oid" : "54752b3a73f0f20126964c13" }, "username" : "user39377", "password" : 3105323, "homedir" : "/home/user39377" }
{ "_id" : { "$oid" : "54752b3a73f0f20126964c14" }, "username" : "user12804", "password" : 2321817, "homedir" : "/home/user12804" }
{ "_id" : { "$oid" : "54752b3a73f0f20126964c15" }, "username" : "user72095", "password" : 7485335, "homedir" : "/home/user72095" }
{ "_id" : { "$oid" : "54752b3a73f0f20126964c16" }, "username" : "user87350", "password" : 4106185, "homedir" : "/home/user87350" }
{ "_id" : { "$oid" : "54752b3a73f0f20126964c17" }, "username" : "user83824", "password" : 9155392, "homedir" : "/home/user83824" }
{ "_id" : { "$oid" : "54752b3a73f0f20126964c18" }, "username" : "user96161", "password" : 8133961, "homedir" : "/home/user96161" }
{ "_id" : { "$oid" : "54752b3a73f0f20126964c19" }, "username" : "user82515", "password" : 9504923, "homedir" : "/home/user82515" }
{ "_id" : { "$oid" : "54752b3a73f0f20126964c1a" }, "username" : "user56494", "password" : 2029894, "homedir" : "/home/user56494" }
{ "_id" : { "$oid" : "54752b3a73f0f20126964c1b" }, "username" : "user59582", "password" : 7321319, "homedir" : "/home/user59582" }
{ "_id" : { "$oid" : "54752b3a73f0f20126964c1c" }, "username" : "user54883", "password" : 2615795, "homedir" : "/home/user54883" }
{ "_id" : { "$oid" : "54752b3a73f0f20126964c1d" }, "username" : "user80860", "password" : 5861208, "homedir" : "/home/user80860" }
{ "_id" : { "$oid" : "54752b3a73f0f20126964c1e" }, "username" : "user23252", "password" : 3734317, "homedir" : "/home/user23252" }
{ "_id" : { "$oid" : "54752b3a73f0f20126964c1f" }, "username" : "user16469", "password" : 7975992, "homedir" : "/home/user16469" }
{ "_id" : { "$oid" : "54752b3a73f0f20126964c20" }, "username" : "user83769", "password" : 3586026, "homedir" : "/home/user83769" }
{ "_id" : { "$oid" : "54752b3a73f0f20126964c21" }, "username" : "user95155", "password" : 6815908, "homedir" : "/home/user95155" }
{ "_id" : { "$oid" : "54752b3a73f0f20126964c22" }, "username" : "user57728", "password" : 6156740, "homedir" : "/home/user57728" }
{ "_id" : { "$oid" : "54752b3a73f0f20126964c23" }, "username" : "user84000", "password" : 7310913, "homedir" : "/home/user84000" }
{ "_id" : { "$oid" : "54752b3a73f0f20126964c24" }, "username" : "user13686", "password" : 8716009, "homedir" : "/home/user13686" }
{ "_id" : { "$oid" : "54752b3a73f0f20126964c25" }, "username" : "user69023", "password" : 4263111, "homedir" : "/home/user69023" }
{ "_id" : { "$oid" : "54752b3a73f0f20126964c26" }, "username" : "user38302", "password" : 9427344, "homedir" : "/home/user38302" }
{ "_id" : { "$oid" : "54752b3a73f0f20126964c27" }, "username" : "user95612", "password" : 3985783, "homedir" : "/home/user95612" }
{ "_id" : { "$oid" : "54752b3a73f0f20126964c28" }, "username" : "user81247", "password" : 2417260, "homedir" : "/home/user81247" }
{ "_id" : { "$oid" : "54752b3a73f0f20126964c29" }, "username" : "user25294", "password" : 2505215, "homedir" : "/home/user25294" }
{ "_id" : { "$oid" : "54752b3a73f0f20126964c2a" }, "username" : "user92628", "password" : 9704632, "homedir" : "/home/user92628" }
{ "_id" : { "$oid" : "54752b3a73f0f20126964c2b" }, "username" : "user66554", "password" : 8862155, "homedir" : "/home/user66554" }
{ "_id" : { "$oid" : "54752b3a73f0f20126964c2c" }, "username" : "user80389", "password" : 2497304, "homedir" : "/home/user80389" }
{ "_id" : { "$oid" : "54752b3a73f0f20126964c2d" }, "username" : "user82029", "password" : 1726751, "homedir" : "/home/user82029" }
{ "_id" : { "$oid" : "54752b3a73f0f20126964c2e" }, "username" : "user91010", "password" : 2727800, "homedir" : "/home/user91010" }
{ "_id" : { "$oid" : "54752b3a73f0f20126964c2f" }, "username" : "user41632", "password" : 9549506, "homedir" : "/home/user41632" }
{ "_id" : { "$oid" : "54752b3a73f0f20126964c30" }, "username" : "user35657", "password" : 1893949, "homedir" : "/home/user35657" }
{ "_id" : { "$oid" : "54752b3a73f0f20126964c31" }, "username" : "user50495", "password" : 2584216, "homedir" : "/home/user50495" }
{ "_id" : { "$oid" : "54752b3a73f0f20126964c32" }, "username" : "user13574", "password" : 2953701, "homedir" : "/home/user13574" }
{ "_id" : { "$oid" : "54752b3a73f0f20126964c33" }, "username" : "user96367", "password" : 8711321, "homedir" : "/home/user96367" }
{ "_id" : { "$oid" : "54752b3a73f0f20126964c34" }, "username" : "user91223", "password" : 7702736, "homedir" : "/home/user91223" }
{ "_id" : { "$oid" : "54752b3a73f0f20126964c35" }, "username" : "user35580", "password" : 8364770, "homedir" : "/home/user35580" }
{ "_id" : { "$oid" : "54752b3a73f0f20126964c36" }, "username" : "user65998", "password" : 6465181, "homedir" : "/home/user65998" }
{ "_id" : { "$oid" : "54752b3a73f0f20126964c37" }, "username" : "user20110", "password" : 7519525, "homedir" : "/home/user20110" }
{ "_id" : { "$oid" : "54752b3a73f0f20126964c38" }, "username" : "user66937", "password" : 9154469, "homedir" : "/home/user66937" }
{ "_id" : { "$oid" : "54752b3a73f0f20126964c39" }, "username" : "user12357", "password" : 7678168, "homedir" : "/home/user12357" }
{ "_id" : { "$oid" : "54752b3a73f0f20126964c3a" }, "username" : "user46102", "password" : 9736587, "homedir" : "/home/user46102" }
{ "_id" : { "$oid" : "54752b3a73f0f20126964c3b" }, "username" : "user81508", "password" : 1292729, "homedir" : "/home/user81508" }
{ "_id" : { "$oid" : "54752b3a73f0f20126964c3c" }, "username" : "user51483", "password" : 2770092, "homedir" : "/home/user51483" }
{ "_id" : { "$oid" : "54752b3a73f0f20126964c3d" }, "username" : "user67594", "password" : 2170841, "homedir" : "/home/user67594" }
{ "_id" : { "$oid" : "54752b3a73f0f20126964c3e" }, "username" : "user78230", "password" : 5752808, "homedir" : "/home/user78230" }
{ "_id" : { "$oid" : "54752b3a73f0f20126964c3f" }, "username" : "user35053", "password" : 4634643, "homedir" : "/home/user35053" }
{ "_id" : { "$oid" : "54752b3a73f0f20126964c40" }, "username" : "user84862", "password" : 3357315, "homedir" : "/home/user84862" }
{ "_id" : { "$oid" : "54752b3a73f0f20126964c41" }, "username" : "user78524", "password" : 9325222, "homedir" : "/home/user78524" }
{ "_id" : { "$oid" : "54752b3a73f0f20126964c42" }, "username" : "user52713", "password" : 4479967, "homedir" : "/home/user52713" }
{ "_id" : { "$oid" : "54752b3a73f0f20126964c43" }, "username" : "user40046", "password" : 7287355, "homedir" : "/home/user40046" }
{ "_id" : { "$oid" : "54752b3a73f0f20126964c44" }, "username" : "user38208", "password" : 2207927, "homedir" : "/home/user38208" }
{ "_id" : { "$oid" : "54752b3a73f0f20126964c45" }, "username" : "user86851", "password" : 1555825, "homedir" : "/home/user86851" }
{ "_id" : { "$oid" : "54752b3a73f0f20126964c46" }, "username" : "user26754", "password" : 8488424, "homedir" : "/home/user26754" }
{ "_id" : { "$oid" : "54752b3a73f0f20126964c47" }, "username" : "user17463", "password" : 4190909, "homedir" : "/home/user17463" }
{ "_id" : { "$oid" : "54752b3a73f0f20126964c48" }, "username" : "user83871", "password" : 8102456, "homedir" : "/home/user83871" }
{ "_id" : { "$oid" : "54752b3a73f0f20126964c49" }, "username" : "user44386", "password" : 6220568, "homedir" : "/home/user44386" }
{ "_id" : { "$oid" : "54752b3a73f0f20126964c4a" }, "username" : "user24476", "password" : 9507778, "homedir" : "/home/user24476" }
{ "_id" : { "$oid" : "54752b3a73f0f20126964c4b" }, "username" : "user25139", "password" : 1482007, "homedir" : "/home/user25139" }
{ "_id" : { "$oid" : "54752b3a73f0f20126964c4c" }, "username" : "user37990", "password" : 1067601, "homedir" : "/home/user37990" }
{ "_id" : { "$oid" : "54752b3a73f0f20126964c4d" }, "username" : "user10739", "password" : 4387209, "homedir" : "/home/user10739" }
{ "_id" : { "$oid" : "54752b3a73f0f20126964c4e" }, "username" : "user42719", "password" : 9788934, "homedir" : "/home/user42719" }
{ "_id" : { "$oid" : "54752b3a73f0f20126964c4f" }, "username" : "user52354", "password" : 8482447, "homedir" : "/home/user52354" }
{ "_id" : { "$oid" : "54752b3a73f0f20126964c50" }, "username" : "user78083", "password" : 2393785, "homedir" : "/home/user78083" }
{ "_id" : { "$oid" : "54752b3a73f0f20126964c51" }, "username" : "user65629", "password" : 3414378, "homedir" : "/home/user65629" }
{ "_id" : { "$oid" : "54752b3a73f0f20126964c52" }, "username" : "user54214", "password" : 7917821, "homedir" : "/home/user54214" }
{ "_id" : { "$oid" : "54752b3a73f0f20126964c53" }, "username" : "user70242", "password" : 7416946, "homedir" : "/home/user70242" }
{ "_id" : { "$oid" : "54752b3a73f0f20126964c54" }, "username" : "user99386", "password" : 5437403, "homedir" : "/home/user99386" }
{ "_id" : { "$oid" : "54752b3a73f0f20126964c55" }, "username" : "user17974", "password" : 8179560, "homedir" : "/home/user17974" }
{ "_id" : { "$oid" : "54752b3a73f0f20126964c56" }, "username" : "user47501", "password" : 4193679, "homedir" : "/home/user47501" }
{ "_id" : { "$oid" : "54752b3a73f0f20126964c57" }, "username" : "user64214", "password" : 3364729, "homedir" : "/home/user64214" }
{ "_id" : { "$oid" : "54752b3a73f0f20126964c58" }, "username" : "user93925", "password" : 9797994, "homedir" : "/home/user93925" }
{ "_id" : { "$oid" : "54752b3a73f0f20126964c59" }, "username" : "user33037", "password" : 9170742, "homedir" : "/home/user33037" }
{ "_id" : { "$oid" : "54752b3a73f0f20126964c5a" }, "username" : "user58963", "password" : 5115623, "homedir" : "/home/user58963" }
{ "_id" : { "$oid" : "54752b3a73f0f20126964c5b" }, "username" : "user99550", "password" : 3620413, "homedir" : "/home/user99550" }
{ "_id" : { "$oid" : "54752b3a73f0f20126964c5c" }, "username" : "user59152", "password" : 3917227, "homedir" : "/home/user59152" }
{ "_id" : { "$oid" : "54752b3a73f0f20126964c5d" }, "username" : "user31800", "password" : 7253557, "homedir" : "/home/user31800" }
{ "_id" : { "$oid" : "54752b3a73f0f20126964c5e" }, "username" : "user14817", "password" : 2566513, "homedir" : "/home/user14817" }
{ "_id" : { "$oid" : "54752b3a73f0f20126964c5f" }, "username" : "user94693", "password" : 1612710, "homedir" : "/home/user94693" }
{ "_id" : { "$oid" : "54752b3a73f0f20126964c60" }, "username" : "user61212", "password" : 8178646, "homedir" : "/home/user61212" }
{ "_id" : { "$oid" : "54752b3a73f0f20126964c61" }, "username" : "user85576", "password" : 8997623, "homedir" : "/home/user85576" }
{ "_id" : { "$oid" : "54752b3a73f0f20126964c62" }, "username" : "user92247", "password" : 5319567, "homedir" : "/home/user92247" }
{ "_id" : { "$oid" : "54752b3a73f0f20126964c63" }, "username" : "user23240", "password" : 8009587, "homedir" : "/home/user23240" }
{ "_id" : { "$oid" : "54752b3a73f0f20126964c64" }, "username" : "user20369", "password" : 3690469, "homedir" : "/home/user20369" }
{ "_id" : { "$oid" : "54752b3a73f0f20126964c65" }, "username" : "user33027", "password" : 6131578, "homedir" : "/home/user33027" }
{ "_id" : { "$oid" : "54752b3a73f0f20126964c67" }, "username" : "user32345", "password" : 8766542, "homedir" : "/home/user32345" }
{ "_id" : { "$oid" : "54752b3a73f0f20126964c68" }, "username" : "user75542", "password" : 9443542, "homedir" : "/home/user75542" }
{ "_id" : { "$oid" : "54752b3a73f0f20126964c69" }, "username" : "user82381", "password" : 9553394, "homedir" : "/home/user82381" }
{ "_id" : { "$oid" : "54752b3a73f0f20126964c6a" }, "username" : "user56570", "password" : 9977268, "homedir" : "/home/user56570" }
{ "_id" : { "$oid" : "54752b3a73f0f20126964c6b" }, "username" : "user38905", "password" : 8229861, "homedir" : "/home/user38905" }
{ "_id" : { "$oid" : "54752b3a73f0f20126964c6c" }, "username" : "user57095", "password" : 9434244, "homedir" : "/home/user57095" }
